[
    {
        "id": 908111702608774386,
        "name": "HARSH CHOUDHARY",
        "email": "1032201678@mitwpu.edu.in",
        "phone_number": "+91-9373687718"
    },
    {
        "id": 3760355020705871101,
        "name": "PRATHAMESH KULKARNI",
        "email": "prathamesh.kulkarni20@vit.edu.in",
        "phone_number": "+91-9137908651"
    },
    {
        "id": 8470051443012795495,
        "name": "Mr. Atharva Ramakrishna",
        "email": "1032201741@mitwpu.edu.in",
        "phone_number": "+91-7887580387"
    },
    {
        "id": 8334388277431027469,
        "name": "IPSITA SOUMYA",
        "email": "1032201909@mitwpu.edu.in",
        "phone_number": "+91-7057570937"
    }
]